mammos_entity/__init__.py
mammos_entity/_base.py
mammos_entity/_entities.py
mammos_entity/_onto.py
mammos_entity/io.py
mammos_entity/operations.py
mammos_entity/py.typed
mammos_entity/ontology/emmo.ttl
mammos_entity/ontology/magnetic_material_mammos.ttl
mammos_entity-0.11.1.dist-info/METADATA
mammos_entity-0.11.1.dist-info/WHEEL
mammos_entity-0.11.1.dist-info/licenses/LICENSE
mammos_entity-0.11.1.dist-info/licenses/LICENSE_ONTOLOGY
mammos_entity-0.11.1.dist-info/RECORD
