Metadata-Version: 2.4
Name: mammos-entity
Version: 0.11.1
Summary: Python package to specify material parameters for MaMMoS simulation suite.
Project-URL: Homepage, https://MaMMoS-project.github.io
Project-URL: Documentation, https://mammos-project.github.io/mammos
Project-URL: Repository, https://github.com/MaMMoS-project/mammos-entity
Project-URL: Issues, https://github.com/MaMMoS-project/mammos-entity/issues
Project-URL: Changelog, https://mammos-project.github.io/mammos/changelog
Author: Swapneel Amit Pathak, Andrea Petrocchi, Sam Holt, Martin Lang, Wilfried Hortschitz, Santa Pile, Martin Dobiasch, Hans Fangohr
License-Expression: MIT AND CC-BY-4.0
License-File: LICENSE
License-File: LICENSE_ONTOLOGY
Classifier: Intended Audience :: Developers
Classifier: Intended Audience :: Education
Classifier: Intended Audience :: Science/Research
Classifier: Programming Language :: Python :: 3 :: Only
Classifier: Topic :: Scientific/Engineering :: Physics
Requires-Python: >=3.11
Requires-Dist: emmontopy>=0.8
Requires-Dist: mammos-units>=0.2.1
Requires-Dist: numpy<3
Requires-Dist: pandas>=2
